<?xml version="1.0" encoding="utf-8" standalone="yes" ?>
<T3DataStructure>
    <sheets>
        <sDEF>
            <ROOT>
                <TCEforms>
                    <sheetTitle>OSM Settings</sheetTitle>
                </TCEforms>
                <type>array</type>
                <el>
                    <settings.mapUid>
                        <TCEforms>
                            <label>Select OSM Map</label>
                            <config>
                                <type>select</type>
                                <foreign_table>tx_pbosmpartners_domain_model_map</foreign_table>
                                <items>
                                    <numIndex index="0" type="array">
                                        <numIndex index="0">-- Choose --</numIndex>
                                        <numIndex index="1"></numIndex>
                                    </numIndex>
                                </items>
                                <size>1</size>
                                <maxitems>1</maxitems>
                                <minitems>0</minitems>
                            </config>
                        </TCEforms>
                    </settings.mapUid>
                </el>
            </ROOT>
        </sDEF>
    </sheets>
</T3DataStructure>
